huaweicloudsdkres/__init__.py
huaweicloudsdkres/v1/__init__.py
huaweicloudsdkres/v1/res_async_client.py
huaweicloudsdkres/v1/res_client.py
huaweicloudsdkres/v1/model/__init__.py
huaweicloudsdkres/v1/model/algorithm_specify_parameters.py
huaweicloudsdkres/v1/model/attr_pair.py
huaweicloudsdkres/v1/model/attr_pair_rules.py
huaweicloudsdkres/v1/model/attr_value.py
huaweicloudsdkres/v1/model/attr_value_rules.py
huaweicloudsdkres/v1/model/attribute.py
huaweicloudsdkres/v1/model/attribute_info.py
huaweicloudsdkres/v1/model/behavior_frequency.py
huaweicloudsdkres/v1/model/behavior_gravity.py
huaweicloudsdkres/v1/model/behavior_weights.py
huaweicloudsdkres/v1/model/behaviors_config.py
huaweicloudsdkres/v1/model/bloom_filter_conf.py
huaweicloudsdkres/v1/model/category.py
huaweicloudsdkres/v1/model/create_res_datasource_request.py
huaweicloudsdkres/v1/model/create_res_datasource_request_body.py
huaweicloudsdkres/v1/model/create_res_datasource_response.py
huaweicloudsdkres/v1/model/create_res_intelligent_scene_request.py
huaweicloudsdkres/v1/model/create_res_intelligent_scene_request_n_body.py
huaweicloudsdkres/v1/model/create_res_intelligent_scene_response.py
huaweicloudsdkres/v1/model/create_res_job_request.py
huaweicloudsdkres/v1/model/create_res_job_request_body.py
huaweicloudsdkres/v1/model/create_res_job_response.py
huaweicloudsdkres/v1/model/create_res_jobs_request.py
huaweicloudsdkres/v1/model/create_res_jobs_reququest_body.py
huaweicloudsdkres/v1/model/create_res_jobs_response.py
huaweicloudsdkres/v1/model/create_res_online_instance_request.py
huaweicloudsdkres/v1/model/create_res_online_instance_request_body.py
huaweicloudsdkres/v1/model/create_res_online_instance_response.py
huaweicloudsdkres/v1/model/create_res_scene_request.py
huaweicloudsdkres/v1/model/create_res_scene_request_body.py
huaweicloudsdkres/v1/model/create_res_scene_response.py
huaweicloudsdkres/v1/model/create_res_workspace_request.py
huaweicloudsdkres/v1/model/create_res_workspace_request_body.py
huaweicloudsdkres-3.1.184.dist-info/METADATA
huaweicloudsdkres-3.1.184.dist-info/WHEEL
huaweicloudsdkres-3.1.184.dist-info/licenses/LICENSE
huaweicloudsdkres-3.1.184.dist-info/RECORD
